[
    {
        "Source ID": "FarFetch",
        "Product URL": "https://www.farfetch.com/sa/shopping/men/d-r-g-n-men-meaning-hoodie-item-25026275.aspx?storeid=9499",
        "Brand": "D-R-G-N",
        "Product Title": "Men Meaning hoodie ",
        "Product ID": "25026275",
        "Category": "Men Home, D-R-G-N, Clothing, Hoodies",
        "Price": "1699",
        "Discount": 711,
        "Currency": "SAR",
        "Description": "D-R-G-N\nMen Meaning hoodie \nMade in United States\nHighlights\nwhite \ncotton \ngraphic print to the front \nlogo print to the rear \nclassic hood \nfront pouch pocket \nlong sleeves \nstraight hem \nComposition\nCotton 100%\nWashing instructions\nDry Clean Only\nProduct IDs\nFARFETCH ID: \n 25026275\nBrand style ID: \n DGAW24PU01",
        "Main Image URL": "https://cdn-images.farfetch-contents.com/25/02/62/75/25026275_55292103_1000.jpg",
        "Other Images URL": [
            "https://cdn-images.farfetch-contents.com/25/02/62/75/25026275_55292101_1000.jpg",
            "https://cdn-images.farfetch-contents.com/25/02/62/75/25026275_55292100_1000.jpg"
        ],
        "Colors": "Neutrals",
        "Variations": "",
        "Sizes": "",
        "Other Details": "",
        "Availability": "In Stock",
        "Number of Items in Stock": 2410,
        "Last Update": "",
        "Creation Date": "2025-01-16 21:13:29"
    },
    {
        "Source ID": "FarFetch",
        "Product URL": "https://www.farfetch.com/sa/shopping/men/cp-company-shell-r-medium-baseball-jacket-item-24772826.aspx?storeid=14279",
        "Brand": "C.P. Company",
        "Product Title": "Shell-R Medium baseball jacket",
        "Product ID": "24772826",
        "Category": "Men Home, C.P. Company, Clothing, Bomber Jackets",
        "Price": "2007",
        "Discount": "",
        "Currency": "SAR",
        "Description": "C.P. Company\nShell-R Medium baseball jacket\nHighlights\nbeluga grey \nfront two-way zip fastening \nstand-up collar \nsignature Lens detail \nsleeve zip pocket \nlong sleeves \nribbed cuffs \ntwo front flap pockets \ntwo side zip-fastening pockets \nfleece lining \nC.P. Company suggests removing any detachable accessories before washing. \nComposition\nOuter: \nPolyester 94%,  \nElastane 6%\nLining: \nPolyester 100%\nWashing instructions\nMachine Wash\nWearing\nThe model is 1.86 m wearing size M\nProduct IDs\nFARFETCH ID: \n 24772826\nBrand style ID: \n 17CMOW006A006097A",
        "Main Image URL": "https://cdn-images.farfetch-contents.com/24/77/28/26/24772826_55048054_1000.jpg",
        "Other Images URL": [
            "https://cdn-images.farfetch-contents.com/24/77/28/26/24772826_55048053_1000.jpg",
            "https://cdn-images.farfetch-contents.com/24/77/28/26/24772826_55048030_1000.jpg",
            "https://cdn-images.farfetch-contents.com/24/77/28/26/24772826_55048048_1000.jpg",
            "https://cdn-images.farfetch-contents.com/24/77/28/26/24772826_55048027_1000.jpg"
        ],
        "Colors": "Grey",
        "Variations": "",
        "Sizes": "",
        "Other Details": "",
        "Availability": "In Stock",
        "Number of Items in Stock": 0,
        "Last Update": "",
        "Creation Date": "2025-01-16 21:13:29"
    },
    {
        "Source ID": "FarFetch",
        "Product URL": "https://www.farfetch.com/sa/shopping/men/a-bathing-ape-sta-3-m1-sneakers-item-19818131.aspx?storeid=14288",
        "Brand": "A BATHING APE®",
        "Product Title": "Sta #3 M1 sneakers",
        "Product ID": "19818131",
        "Category": "Men Home, A BATHING APE®, Shoes, Low-Tops",
        "Price": "1686",
        "Discount": "",
        "Currency": "SAR",
        "Description": "A BATHING APE®\nSta #3 M1 sneakers\nA brand's signature style, the BAPE STA #3 M1 sneakers from BAPE arrive in a tonal turquoise colourway. This model features a classic low-top silhouette, made from leather, and is highlighted by the iconic BAPE STA™ logo on the sides in a darker hue. Underneath, a two-tone rubber sole completes the look.\nHighlights\nturquoise blue-green \nleather \nsignature BAPE STA™ logo \nround toe \nfront lace-up fastening \nlogo patch at the tongue \nbranded insole \nrubber sole \nThese styles are supplied by a premium sneaker marketplace. Stocking only the most sought-after footwear, they source and curate some of the most hard to find sneakers from around the world. \nComposition\nOuter: \nLeather 100%\nLining: \nLeather 100%\nSole: \nRubber 100%\nProduct IDs\nFARFETCH ID: \n 19818131\nBrand style ID: \n 0ZXSHM191008JGRD",
        "Main Image URL": "https://cdn-images.farfetch-contents.com/19/81/81/31/19818131_44801418_1000.jpg",
        "Other Images URL": [
            "https://cdn-images.farfetch-contents.com/19/81/81/31/19818131_44801417_1000.jpg",
            "https://cdn-images.farfetch-contents.com/19/81/81/31/19818131_44800928_1000.jpg",
            "https://cdn-images.farfetch-contents.com/19/81/81/31/19818131_44800927_1000.jpg",
            "https://cdn-images.farfetch-contents.com/19/81/81/31/19818131_44801416_1000.jpg"
        ],
        "Colors": "Blue",
        "Variations": "",
        "Sizes": "",
        "Other Details": "",
        "Availability": "In Stock",
        "Number of Items in Stock": 1,
        "Last Update": "",
        "Creation Date": "2025-01-16 21:13:31"
    },
    {
        "Source ID": "FarFetch",
        "Product URL": "https://www.farfetch.com/sa/shopping/men/chateau-lafleur-gazin-single-breasted-wool-suit-item-20053854.aspx?storeid=9026",
        "Brand": " Château Lafleur-Gazin",
        "Product Title": "single-breasted wool suit ",
        "Product ID": "20053854",
        "Category": "Men Home,  Château Lafleur-Gazin, Clothing, Single Breasted Suits",
        "Price": "3103",
        "Discount": "",
        "Currency": "SAR",
        "Description": " Château Lafleur-Gazin\nsingle-breasted wool suit \nMade in Italy\nHighlights\nblack \nwool \nJacket:\npeak lapels \nfront button fastening \ntwo front welt pockets \nchest welt pocket \nlong sleeves \nbuttoned-cuff sleeves \nstraight hem \nTrousers:\nbelt loops \npressed crease \ntailored cut \ntwo side inset pockets \ntwo rear welt pockets \nComposition\nOuter: \nWool 100%\nLining: \nViscose 100%\nWashing instructions\nDry Clean Only\nWearing\nThe model is 1.86 m wearing size 48\nProduct IDs\nFARFETCH ID: \n 20053854\nBrand style ID: \n V50664508",
        "Main Image URL": "https://cdn-images.farfetch-contents.com/20/05/38/54/20053854_45193798_1000.jpg",
        "Other Images URL": [
            "https://cdn-images.farfetch-contents.com/20/05/38/54/20053854_45195218_1000.jpg",
            "https://cdn-images.farfetch-contents.com/20/05/38/54/20053854_45193800_1000.jpg",
            "https://cdn-images.farfetch-contents.com/20/05/38/54/20053854_45195217_1000.jpg",
            "https://cdn-images.farfetch-contents.com/20/05/38/54/20053854_45193799_1000.jpg"
        ],
        "Colors": "Black",
        "Variations": "",
        "Sizes": "",
        "Other Details": "",
        "Availability": "In Stock",
        "Number of Items in Stock": 0,
        "Last Update": "",
        "Creation Date": "2025-01-16 21:13:35"
    },
    {
        "Source ID": "FarFetch",
        "Product URL": "https://www.farfetch.com/sa/shopping/men/y-3-ultraboost-5-sneakers-item-25350201.aspx?storeid=14928",
        "Brand": "Y-3",
        "Product Title": "Ultraboost 5 sneakers",
        "Product ID": "25350201",
        "Category": "Men Home, Y-3, Shoes, Low-Tops",
        "Price": "1241",
        "Discount": "",
        "Currency": "SAR",
        "Description": "Y-3\nUltraboost 5 sneakers\nMade in Italy\nHighlights\nwhite \nPrimeknit construction \npanelled design \nfront lace-up fastening \nsock-style ankle \nbranded heel counter \nlogo patch to the side \nalmond toe \nbranded insole \nsignature cushioned Boost midsole \nrubber sole \nContinental™ rubber outsole \nComposition\nLining: \nFabric 100%\nSole: \nRubber 100%\nOuter: \nFabric 100%\nProduct IDs\nFARFETCH ID: \n 25350201\nBrand style ID: \n IH0870",
        "Main Image URL": "https://cdn-images.farfetch-contents.com/25/35/02/01/25350201_55684504_1000.jpg",
        "Other Images URL": [
            "https://cdn-images.farfetch-contents.com/25/35/02/01/25350201_55683654_1000.jpg",
            "https://cdn-images.farfetch-contents.com/25/35/02/01/25350201_55683652_1000.jpg",
            "https://cdn-images.farfetch-contents.com/25/35/02/01/25350201_55683658_1000.jpg"
        ],
        "Colors": "White",
        "Variations": "",
        "Sizes": "",
        "Other Details": "",
        "Availability": "In Stock",
        "Number of Items in Stock": 5,
        "Last Update": "",
        "Creation Date": "2025-01-16 21:13:46"
    },
    {
        "Source ID": "FarFetch",
        "Product URL": "https://www.farfetch.com/sa/shopping/men/v73-logo-detail-travel-case-item-19993208.aspx?storeid=9885",
        "Brand": "V°73",
        "Product Title": "logo-detail travel case",
        "Product ID": "19993208",
        "Category": "Men Home, V°73, Bags, Luggage & Holdalls",
        "Price": "552",
        "Discount": 59,
        "Currency": "SAR",
        "Description": "V°73\nlogo-detail travel case\nHighlights\nblack \nlogo print to the front \nall-over graphic print \nall-around zip fastening \nfour wheels \nmain compartment \ninternal zip-fastening pockets \nComposition\nOuter: \nAcrylic 100%,  \nAcrylonitrile Butadiene Styrene (ABS) 100%\nLining: \nPolyester 100%\nProduct IDs\nFARFETCH ID: \n 19993208\nBrand style ID: \n 73V73201P",
        "Main Image URL": "https://cdn-images.farfetch-contents.com/19/99/32/08/19993208_45015657_1000.jpg",
        "Other Images URL": [
            "https://cdn-images.farfetch-contents.com/19/99/32/08/19993208_45017694_1000.jpg",
            "https://cdn-images.farfetch-contents.com/19/99/32/08/19993208_45015656_1000.jpg",
            "https://cdn-images.farfetch-contents.com/19/99/32/08/19993208_45015655_1000.jpg",
            "https://cdn-images.farfetch-contents.com/19/99/32/08/19993208_45016839_1000.jpg"
        ],
        "Colors": "Black",
        "Variations": "",
        "Sizes": "",
        "Other Details": "",
        "Availability": "In Stock",
        "Number of Items in Stock": 611,
        "Last Update": "",
        "Creation Date": "2025-01-16 21:13:50"
    },
    {
        "Source ID": "FarFetch",
        "Product URL": "https://www.farfetch.com/sa/shopping/men/xacus-stretch-design-shirt-item-23280518.aspx?storeid=9446",
        "Brand": "Xacus",
        "Product Title": "stretch-design shirt",
        "Product ID": "23280518",
        "Category": "Men Home, Xacus, Clothing, Shirts",
        "Price": "320",
        "Discount": 394,
        "Currency": "SAR",
        "Description": "Xacus\nstretch-design shirt\nHighlights\nnavy blue \nstretch-design \nseersucker texture \nspread collar \nlong sleeves \nbuttoned-cuff sleeves \ncurved hem \nfront button fastening \nComposition\nPolyamide 86%,  \nSpandex/Elastane 14%\nWashing instructions\nMachine Wash\nProduct IDs\nFARFETCH ID: \n 23280518\nBrand style ID: \n 61616ACT748ML",
        "Main Image URL": "https://cdn-images.farfetch-contents.com/23/28/05/18/23280518_53408492_1000.jpg",
        "Other Images URL": [
            "https://cdn-images.farfetch-contents.com/23/28/05/18/23280518_53408503_1000.jpg"
        ],
        "Colors": "Blue",
        "Variations": "",
        "Sizes": "",
        "Other Details": "",
        "Availability": "In Stock",
        "Number of Items in Stock": 1,
        "Last Update": "",
        "Creation Date": "2025-01-16 21:13:52"
    },
    {
        "Source ID": "FarFetch",
        "Product URL": "https://www.farfetch.com/sa/shopping/men/zadigvoltaire-mate-shearling-collar-leather-jacket-item-20204328.aspx?storeid=12859",
        "Brand": "Zadig&amp;Voltaire",
        "Product Title": "Mate shearling-collar leather jacket ",
        "Product ID": "20204328",
        "Category": "Men Home, Zadig&Voltaire, Clothing, Leather Jackets",
        "Price": "4566",
        "Discount": "",
        "Currency": "SAR",
        "Description": "Zadig&Voltaire\nMate shearling-collar leather jacket \nCrafted from leather, this jacket from Zadig&amp;Voltaire brings warmth and elegance. It features a shearling collar and a front-zip closure. \nHighlights\nchestnut brown/camel brown \ncalf leather \ndistressed finish \nshearling collar \nfront zip fastening \nlong sleeves \ntwo front flap pockets \nribbed cuffs and hem \nstraight hem \nWhen buying this unisex item, keep in mind that it is graded in standard men's sizing. \nComposition\nGoat Skin 100%\nWashing instructions\nSpecialist Cleaning\nWearing\nThe model is 1.79 m wearing size M\nProduct IDs\nFARFETCH ID: \n 20204328\nBrand style ID: \n RMOW00099",
        "Main Image URL": "https://cdn-images.farfetch-contents.com/20/20/43/28/20204328_51548077_1000.jpg",
        "Other Images URL": [
            "https://cdn-images.farfetch-contents.com/20/20/43/28/20204328_51548089_1000.jpg",
            "https://cdn-images.farfetch-contents.com/20/20/43/28/20204328_51548087_1000.jpg",
            "https://cdn-images.farfetch-contents.com/20/20/43/28/20204328_51548094_1000.jpg",
            "https://cdn-images.farfetch-contents.com/20/20/43/28/20204328_51548095_1000.jpg"
        ],
        "Colors": "Brown",
        "Variations": "",
        "Sizes": "",
        "Other Details": "",
        "Availability": "In Stock",
        "Number of Items in Stock": 0,
        "Last Update": "",
        "Creation Date": "2025-01-16 21:13:53"
    },
    {
        "Source ID": "FarFetch",
        "Product URL": "https://www.farfetch.com/sa/shopping/men/wacko-maria-logo-print-hoodie-item-26803987.aspx?storeid=12949",
        "Brand": "WACKO MARIA",
        "Product Title": "logo-print hoodie",
        "Product ID": "26803987",
        "Category": "Men Home, WACKO MARIA, Clothing, Hoodies",
        "Price": "898",
        "Discount": "",
        "Currency": "SAR",
        "Description": "WACKO MARIA\nlogo-print hoodie\nHighlights\nblack/white \ndrawstring hood \ndrop shoulder \nlong sleeves \nlogo print at the chest \nfront pouch pocket \nribbed trim \nstraight hem \nComposition\nFabric 100%\nWashing instructions\nRead Manufacturer Guidelines\nProduct IDs\nFARFETCH ID: \n 26803987\nBrand style ID: \n 24SSWMCSS14",
        "Main Image URL": "https://cdn-images.farfetch-contents.com/26/80/39/87/26803987_57021736_1000.jpg",
        "Other Images URL": [
            "https://cdn-images.farfetch-contents.com/26/80/39/87/26803987_57021733_1000.jpg"
        ],
        "Colors": "Black",
        "Variations": "",
        "Sizes": "",
        "Other Details": "",
        "Availability": "In Stock",
        "Number of Items in Stock": 0,
        "Last Update": "",
        "Creation Date": "2025-01-16 21:13:54"
    },
    {
        "Source ID": "FarFetch",
        "Product URL": "https://www.farfetch.com/sa/shopping/men/ugg-tasman-suede-slippers-item-19606190.aspx?storeid=9728",
        "Brand": "UGG",
        "Product Title": "Tasman suede slippers",
        "Product ID": "19606190",
        "Category": "Men Home, UGG, Shoes, Slippers",
        "Price": "473",
        "Discount": "",
        "Currency": "SAR",
        "Description": "UGG\nTasman suede slippers\nThe Tasman slippers are a popular silhouette of the Australian brand UGG. This chestnut brown iteration is crafted from a supple suede outer, lined with a plush shearling interior that offers a warm and cosy sensation. Underfoot, a thick rubber sole allows for both outdoor and indoor use.\nHighlights\nchestnut brown \nsuede \nbraided edge \nslip-on style \ndebossed logo to the side \nround toe \nshearling lining \nflat rubber sole \nComposition\nOuter: \nCalf Suede 100%\nLining: \nRecycled Polyester 100%,  \nWool 60%,  \nLyocell 40%\nSole: \nRubber 100%\nProduct IDs\nFARFETCH ID: \n 19606190\nBrand style ID: \n 5950CHE",
        "Main Image URL": "https://cdn-images.farfetch-contents.com/19/60/61/90/19606190_43747448_1000.jpg",
        "Other Images URL": [
            "https://cdn-images.farfetch-contents.com/19/60/61/90/19606190_43747442_1000.jpg",
            "https://cdn-images.farfetch-contents.com/19/60/61/90/19606190_43748484_1000.jpg",
            "https://cdn-images.farfetch-contents.com/19/60/61/90/19606190_43748489_1000.jpg"
        ],
        "Colors": "Brown",
        "Variations": "",
        "Sizes": "",
        "Other Details": "",
        "Availability": "In Stock",
        "Number of Items in Stock": 0,
        "Last Update": "",
        "Creation Date": "2025-01-16 21:14:01"
    },
    {
        "Source ID": "FarFetch",
        "Product URL": "https://www.farfetch.com/sa/shopping/men/qasimi-caligraphy-t-shirt-item-24546815.aspx?storeid=11918",
        "Brand": "Qasimi",
        "Product Title": "Caligraphy t-shirt ",
        "Product ID": "24546815",
        "Category": "Men Home, Qasimi, Clothing, T-Shirts",
        "Price": "593",
        "Discount": 255,
        "Currency": "SAR",
        "Description": "Qasimi\nCaligraphy t-shirt \nHighlights\nbeige \ncotton \ncrew neck \nembroidered lettering \nshort sleeves \nstraight hem \nslogan print to the rear \nComposition\nCotton 100%\nWashing instructions\nRead Manufacturer Guidelines\nProduct IDs\nFARFETCH ID: \n 24546815\nBrand style ID: \n AW24JE12",
        "Main Image URL": "https://cdn-images.farfetch-contents.com/24/54/68/15/24546815_55032149_1000.jpg",
        "Other Images URL": [
            "https://cdn-images.farfetch-contents.com/24/54/68/15/24546815_55032151_1000.jpg",
            "https://cdn-images.farfetch-contents.com/24/54/68/15/24546815_55032153_1000.jpg",
            "https://cdn-images.farfetch-contents.com/24/54/68/15/24546815_55032150_1000.jpg",
            "https://cdn-images.farfetch-contents.com/24/54/68/15/24546815_55032158_1000.jpg"
        ],
        "Colors": "Neutrals",
        "Variations": "",
        "Sizes": "",
        "Other Details": "",
        "Availability": "In Stock",
        "Number of Items in Stock": 1,
        "Last Update": "",
        "Creation Date": "2025-01-16 21:14:06"
    },
    {
        "Source ID": "FarFetch",
        "Product URL": "https://www.farfetch.com/sa/shopping/men/t-henri-taycan-sunglasses-item-24852999.aspx?storeid=14720",
        "Brand": "T HENRI",
        "Product Title": "Taycan sunglasses",
        "Product ID": "24852999",
        "Category": "Men Home, T HENRI, Accessories, Sunglasses",
        "Price": "3881",
        "Discount": "",
        "Currency": "SAR",
        "Description": "T HENRI\nTaycan sunglasses\nHighlights\nblack \nrectangle frame \nUV-protective gradient lenses \nlogo lens decal \nengraved logo \nstraight arms with curved tips \nThese glasses come with a protective case. \nComposition\nAcetate 100%\nProduct IDs\nFARFETCH ID: \n 24852999\nBrand style ID: \n TAYCAN",
        "Main Image URL": "https://cdn-images.farfetch-contents.com/24/85/29/99/24852999_55404777_1000.jpg",
        "Other Images URL": [
            "https://cdn-images.farfetch-contents.com/24/85/29/99/24852999_55404761_1000.jpg",
            "https://cdn-images.farfetch-contents.com/24/85/29/99/24852999_55404764_1000.jpg"
        ],
        "Colors": "Black",
        "Variations": "",
        "Sizes": "",
        "Other Details": "",
        "Availability": "In Stock",
        "Number of Items in Stock": 1,
        "Last Update": "",
        "Creation Date": "2025-01-16 21:14:08"
    },
    {
        "Source ID": "FarFetch",
        "Product URL": "https://www.farfetch.com/sa/shopping/men/sns-herning-stark-button-cardigan-item-13521949.aspx?storeid=13109",
        "Brand": "S.N.S. Herning",
        "Product Title": "stark button cardigan",
        "Product ID": "13521949",
        "Category": "Men Home, S.N.S. Herning, Clothing, Cardigans",
        "Price": "1158",
        "Discount": "",
        "Currency": "SAR",
        "Description": "S.N.S. Herning\nstark button cardigan\nNavy blue  merino wool  stark button cardigan from S.N.S. Herning featuring a ribbed roll neck, a front button fastening, waffle textured details, long sleeves and ribbed cuffs. \nComposition\nMerino 100%\nWashing instructions\nHand Wash\nWearing\nThe model is 1.86 m wearing size M\nProduct IDs\nFARFETCH ID: \n 13521949\nBrand style ID: \n 67800C",
        "Main Image URL": "https://cdn-images.farfetch-contents.com/13/52/19/49/13521949_16023869_1000.jpg",
        "Other Images URL": [
            "https://cdn-images.farfetch-contents.com/13/52/19/49/13521949_16023872_1000.jpg",
            "https://cdn-images.farfetch-contents.com/13/52/19/49/13521949_16023876_1000.jpg",
            "https://cdn-images.farfetch-contents.com/13/52/19/49/13521949_16023879_1000.jpg",
            "https://cdn-images.farfetch-contents.com/13/52/19/49/13521949_16023881_1000.jpg"
        ],
        "Colors": "Blue",
        "Variations": "",
        "Sizes": "",
        "Other Details": "",
        "Availability": "In Stock",
        "Number of Items in Stock": 0,
        "Last Update": "",
        "Creation Date": "2025-01-16 21:14:08"
    },
    {
        "Source ID": "FarFetch",
        "Product URL": "https://www.farfetch.com/sa/shopping/men/rmwilliams-drover-leather-belt-item-16352681.aspx?storeid=12713",
        "Brand": "R.M.Williams",
        "Product Title": "Drover leather belt",
        "Product ID": "16352681",
        "Category": "Men Home, R.M.Williams, Accessories, Belts",
        "Price": "397",
        "Discount": "",
        "Currency": "SAR",
        "Description": "R.M.Williams\nDrover leather belt\nchocolate brown leather debossed logo engraved logo on buckle adjustable fit punched holes buckle fastening\nComposition\nBovine Leather (top grain) 100%\nProduct IDs\nFARFETCH ID: \n 16352681\nBrand style ID: \n BSF5ZCH01",
        "Main Image URL": "https://cdn-images.farfetch-contents.com/16/35/26/81/16352681_31735806_1000.jpg",
        "Other Images URL": [
            "https://cdn-images.farfetch-contents.com/16/35/26/81/16352681_31734915_1000.jpg",
            "https://cdn-images.farfetch-contents.com/16/35/26/81/16352681_31734918_1000.jpg"
        ],
        "Colors": "Brown",
        "Variations": "",
        "Sizes": "",
        "Other Details": "",
        "Availability": "In Stock",
        "Number of Items in Stock": 0,
        "Last Update": "",
        "Creation Date": "2025-01-16 21:14:20"
    },
    {
        "Source ID": "FarFetch",
        "Product URL": "https://www.farfetch.com/sa/shopping/men/oakley-sub-temp-rc-gore-tex-20-jacket-item-26621157.aspx?storeid=9671",
        "Brand": "Oakley",
        "Product Title": "Sub Temp RC Gore-Tex 2.0. jacket",
        "Product ID": "26621157",
        "Category": "Men Home, Oakley, Activewear, Ski Jackets",
        "Price": "2335",
        "Discount": "",
        "Currency": "SAR",
        "Description": "Oakley\nSub Temp RC Gore-Tex 2.0. jacket\nHighlights\nlight beige \ntextured finish \nconcealed front touch-strap fastening \nconcealed front zip fastening \ndetachable hood \nlong sleeves \nsleeve zip pocket \nthumb slot \nlogo print to the front \nzip-fastening chest pocket \ntwo side zip-fastening pockets \nstraight hem \nComposition\nOuter: \nPolyester 100%,  \nPolyamide 100%\nLining: \nPolyamide 100%,  \nPolyester 100%\nWashing instructions\nMachine Wash\nWearing\nThe model is 1.86 m wearing size M\nProduct IDs\nFARFETCH ID: \n 26621157\nBrand style ID: \n FOA406100",
        "Main Image URL": "https://cdn-images.farfetch-contents.com/26/62/11/57/26621157_56274282_1000.jpg",
        "Other Images URL": [
            "https://cdn-images.farfetch-contents.com/26/62/11/57/26621157_56274307_1000.jpg",
            "https://cdn-images.farfetch-contents.com/26/62/11/57/26621157_56274323_1000.jpg",
            "https://cdn-images.farfetch-contents.com/26/62/11/57/26621157_56274292_1000.jpg",
            "https://cdn-images.farfetch-contents.com/26/62/11/57/26621157_56274297_1000.jpg"
        ],
        "Colors": "Neutrals",
        "Variations": "",
        "Sizes": "",
        "Other Details": "",
        "Availability": "In Stock",
        "Number of Items in Stock": 1,
        "Last Update": "",
        "Creation Date": "2025-01-16 21:14:27"
    },
    {
        "Source ID": "FarFetch",
        "Product URL": "https://www.farfetch.com/sa/shopping/men/parosh-bead-embellished-camp-collar-shirt-item-23370616.aspx?storeid=11236",
        "Brand": "P.A.R.O.S.H.",
        "Product Title": "bead embellished camp-collar shirt",
        "Product ID": "23370616",
        "Category": "Men Home, P.A.R.O.S.H., Clothing, Shirts",
        "Price": "955",
        "Discount": 478,
        "Currency": "SAR",
        "Description": "P.A.R.O.S.H.\nbead embellished camp-collar shirt\nHighlights\nblack \ntonal stitching \nbead embellishment palm tree  \nembroidered logo to the rear \ncamp collar \nshort sleeves \nshort side slits \nstraight hem \nfront button fastening \nWhen buying this unisex item, keep in mind that it is graded in standard men's sizing. \nComposition\nViscose 100%\nWashing instructions\nDry Clean Only\nWearing\nThe model is 1.75 m wearing size S\nProduct IDs\nFARFETCH ID: \n 23370616\nBrand style ID: \n RALMD380612",
        "Main Image URL": "https://cdn-images.farfetch-contents.com/23/37/06/16/23370616_53456611_1000.jpg",
        "Other Images URL": [
            "https://cdn-images.farfetch-contents.com/23/37/06/16/23370616_53456583_1000.jpg",
            "https://cdn-images.farfetch-contents.com/23/37/06/16/23370616_53456582_1000.jpg",
            "https://cdn-images.farfetch-contents.com/23/37/06/16/23370616_53456594_1000.jpg",
            "https://cdn-images.farfetch-contents.com/23/37/06/16/23370616_53456593_1000.jpg"
        ],
        "Colors": "Black",
        "Variations": "",
        "Sizes": "",
        "Other Details": "",
        "Availability": "In Stock",
        "Number of Items in Stock": 1433,
        "Last Update": "",
        "Creation Date": "2025-01-16 21:14:33"
    },
    {
        "Source ID": "FarFetch",
        "Product URL": "https://www.farfetch.com/sa/shopping/men/nhoolywood-logo-applique-hoodie-item-24879591.aspx?storeid=11810",
        "Brand": "N.HOOLYWOOD",
        "Product Title": "logo-appliqué hoodie",
        "Product ID": "24879591",
        "Category": "Men Home, N.HOOLYWOOD, Clothing, Hoodies",
        "Price": "751",
        "Discount": "",
        "Currency": "SAR",
        "Description": "N.HOOLYWOOD\nlogo-appliqué hoodie\nHighlights\nblack \njersey texture \ndrawstring hood \ndrop shoulder \nlong sleeves \nappliqué logo \nfront pouch pocket \nstraight hem \nComposition\nPolyester 63%,  \nCotton 32%,  \nPolyurethane 5%\nWashing instructions\nRead Manufacturer Guidelines\nProduct IDs\nFARFETCH ID: \n 24879591\nBrand style ID: \n 9242CS80",
        "Main Image URL": "https://cdn-images.farfetch-contents.com/24/87/95/91/24879591_54919850_1000.jpg",
        "Other Images URL": [
            "https://cdn-images.farfetch-contents.com/24/87/95/91/24879591_54919834_1000.jpg"
        ],
        "Colors": "Black",
        "Variations": "",
        "Sizes": "",
        "Other Details": "",
        "Availability": "In Stock",
        "Number of Items in Stock": 0,
        "Last Update": "",
        "Creation Date": "2025-01-16 21:14:35"
    },
    {
        "Source ID": "FarFetch",
        "Product URL": "https://www.farfetch.com/sa/shopping/men/mcohen-perla-marinia-chain-pearl-necklace-item-16919771.aspx?storeid=13537",
        "Brand": "M.Cohen",
        "Product Title": "Perla Marinia chain-pearl necklace",
        "Product ID": "16919771",
        "Category": "Men Home, M.Cohen, Jewelry, Necklaces",
        "Price": "2470",
        "Discount": "",
        "Currency": "SAR",
        "Description": "M.Cohen\nPerla Marinia chain-pearl necklace\nsilver sterling silver/south sea pearl cable-link chain south sea pearl T-bar fastening\nMade in United States\nComposition\nSouth Sea Pearl,  \nSilver\nWearing\nThe model is 1.87 m wearing size OS\nProduct IDs\nFARFETCH ID: \n 16919771\nBrand style ID: \n N104125SLVPRL",
        "Main Image URL": "https://cdn-images.farfetch-contents.com/16/91/97/71/16919771_35574791_1000.jpg",
        "Other Images URL": [
            "https://cdn-images.farfetch-contents.com/16/91/97/71/16919771_35574789_1000.jpg",
            "https://cdn-images.farfetch-contents.com/16/91/97/71/16919771_35576824_1000.jpg"
        ],
        "Colors": "White",
        "Variations": "",
        "Sizes": "",
        "Other Details": "",
        "Availability": "In Stock",
        "Number of Items in Stock": 0,
        "Last Update": "",
        "Creation Date": "2025-01-16 21:14:40"
    },
    {
        "Source ID": "FarFetch",
        "Product URL": "https://www.farfetch.com/sa/shopping/men/la-eyeworks-quinto-gemetric-frame-eyeglasses-item-18573801.aspx?storeid=11485",
        "Brand": "L.A. EYEWORKS",
        "Product Title": "Quinto gemetric-frame eyeglasses",
        "Product ID": "18573801",
        "Category": "Men Home, L.A. EYEWORKS, Accessories, Glasses & Frames",
        "Price": "1869",
        "Discount": "",
        "Currency": "SAR",
        "Description": "L.A. EYEWORKS\nQuinto gemetric-frame eyeglasses\nQuinto gemetric-frame eyeglasses from L.A. EYEWORKS featuring jade green, marbled pattern, geometric frame and curved arms. These glasses come with a protective case..\nComposition\nAcetate 100%\nProduct IDs\nFARFETCH ID: \n 18573801\nBrand style ID: \n QUINTO",
        "Main Image URL": "https://cdn-images.farfetch-contents.com/18/57/38/01/18573801_40130176_1000.jpg",
        "Other Images URL": [
            "https://cdn-images.farfetch-contents.com/18/57/38/01/18573801_40129175_1000.jpg",
            "https://cdn-images.farfetch-contents.com/18/57/38/01/18573801_40129174_1000.jpg"
        ],
        "Colors": "Green",
        "Variations": "",
        "Sizes": "",
        "Other Details": "",
        "Availability": "In Stock",
        "Number of Items in Stock": 1,
        "Last Update": "",
        "Creation Date": "2025-01-16 21:14:48"
    },
    {
        "Source ID": "FarFetch",
        "Product URL": "https://www.farfetch.com/sa/shopping/men/j-koo-v-neck-waistcoat-item-23730752.aspx?storeid=12638",
        "Brand": "J Koo",
        "Product Title": "V-neck waistcoat",
        "Product ID": "23730752",
        "Category": "Men Home, J Koo, Clothing, Waistcoats & Gilets",
        "Price": "1256",
        "Discount": 654,
        "Currency": "SAR",
        "Description": "J Koo\nV-neck waistcoat\nHighlights\nblack \nV-neck \nfront button fastening \nsleeveless \ntwo side zip-fastening pockets \nadjustable strap to the rear \nasymmetric hem \nComposition\nOuter: \nPolyester 100%\nLining: \nPolyester 100%\nWashing instructions\nDry Clean Only\nProduct IDs\nFARFETCH ID: \n 23730752\nBrand style ID: \n J24SSVE401BK",
        "Main Image URL": "https://cdn-images.farfetch-contents.com/23/73/07/52/23730752_53756292_1000.jpg",
        "Other Images URL": [
            "https://cdn-images.farfetch-contents.com/23/73/07/52/23730752_53756291_1000.jpg"
        ],
        "Colors": "Black",
        "Variations": "",
        "Sizes": "",
        "Other Details": "",
        "Availability": "In Stock",
        "Number of Items in Stock": 1,
        "Last Update": "",
        "Creation Date": "2025-01-16 21:14:49"
    },
    {
        "Source ID": "FarFetch",
        "Product URL": "https://www.farfetch.com/sa/shopping/men/k-swiss-logo-print-jacket-item-23884492.aspx?storeid=10704",
        "Brand": "K Swiss",
        "Product Title": "logo print jacket",
        "Product ID": "23884492",
        "Category": "Men Home, K Swiss, Clothing, Lightweight Jackets",
        "Price": "394",
        "Discount": 129,
        "Currency": "SAR",
        "Description": "K Swiss\nlogo print jacket\nHighlights\nblack \nglossy finish \nlogo print at the arm \npatch detail \nhigh neck \nzip fastening \nelasticated drawstring waistband \nComposition\nLining: \nPolyester 100%\nOuter: \nPolyester 100%\nWashing instructions\nMachine Wash\nWearing\nThe model is 1.87 m wearing size M\nProduct IDs\nFARFETCH ID: \n 23884492\nBrand style ID: \n K172456",
        "Main Image URL": "https://cdn-images.farfetch-contents.com/23/88/44/92/23884492_53973467_1000.jpg",
        "Other Images URL": [
            "https://cdn-images.farfetch-contents.com/23/88/44/92/23884492_53973468_1000.jpg",
            "https://cdn-images.farfetch-contents.com/23/88/44/92/23884492_53973475_1000.jpg",
            "https://cdn-images.farfetch-contents.com/23/88/44/92/23884492_53973465_1000.jpg",
            "https://cdn-images.farfetch-contents.com/23/88/44/92/23884492_53973463_1000.jpg"
        ],
        "Colors": "Black",
        "Variations": "",
        "Sizes": "",
        "Other Details": "",
        "Availability": "In Stock",
        "Number of Items in Stock": 523,
        "Last Update": "",
        "Creation Date": "2025-01-16 21:14:53"
    },
    {
        "Source ID": "FarFetch",
        "Product URL": "https://www.farfetch.com/sa/shopping/men/ic-berlin-x-the-rolling-stones-collectors-edition-sunglasses-item-27332773.aspx?storeid=9945",
        "Brand": "Ic! Berlin",
        "Product Title": "x The Rolling Stones Collector’s Edition sunglasses",
        "Product ID": "27332773",
        "Category": "Men Home, Ic! Berlin, Accessories, Sunglasses",
        "Price": "10726",
        "Discount": "",
        "Currency": "SAR",
        "Description": "New Season\nIc! Berlin\nx The Rolling Stones Collector’s Edition sunglasses\nHighlights\nblack \nnose pads \ncurved tips \nThese glasses come with a protective case. \nComposition\nMetal 100%\nProduct IDs\nFARFETCH ID: \n 27332773\nBrand style ID: \n ROLLINGSTONESPECIALEDITION",
        "Main Image URL": "https://cdn-images.farfetch-contents.com/27/33/27/73/27332773_57301729_1000.jpg",
        "Other Images URL": [
            "https://cdn-images.farfetch-contents.com/27/33/27/73/27332773_57301917_1000.jpg",
            "https://cdn-images.farfetch-contents.com/27/33/27/73/27332773_57301940_1000.jpg",
            "https://cdn-images.farfetch-contents.com/27/33/27/73/27332773_57301966_1000.jpg",
            "https://cdn-images.farfetch-contents.com/27/33/27/73/27332773_57301757_1000.jpg"
        ],
        "Colors": "Black",
        "Variations": "",
        "Sizes": "",
        "Other Details": "",
        "Availability": "In Stock",
        "Number of Items in Stock": 1,
        "Last Update": "",
        "Creation Date": "2025-01-16 21:14:54"
    },
    {
        "Source ID": "FarFetch",
        "Product URL": "https://www.farfetch.com/sa/shopping/men/fp-journe-2015-pre-owned-chronometre-souverain-boutique-edition-40mm-item-27565672.aspx?storeid=15251",
        "Brand": "F.P. Journe",
        "Product Title": "2015 pre-owned Chronomètre Souverain Boutique Edition 40mm",
        "Product ID": "27565672",
        "Category": "Men Home, F.P. Journe, Pre-Owned, Pre-Owned Dress Watches",
        "Price": "768121",
        "Discount": "",
        "Currency": "SAR",
        "Description": "F.P. Journe\n2015 pre-owned Chronomètre Souverain Boutique Edition 40mm\nHighlights\n2015 \npre-owned \n40mm \nblack \n18kt rose gold \nround face \nArabic dial \nbaton hands \nseconds sub-dial \nmanual-winding movement \npower reserve indicator \nscrew-down crown \nleather strap \npin-buckle fastening \nThis item comes with a standard one-year warranty from the boutique. \nOriginal box and papers included. \nCondition: UNWORN. This item is previously owned but remains unworn and in its original condition. However, it does not come with its original tags. \nComposition\n18kt Rose Gold 100%,  \nLeather 100%\nProduct IDs\nFARFETCH ID: \n 27565672\nBrand style ID: \n CHRONOMTRESOUVERAIN",
        "Main Image URL": "https://cdn-images.farfetch-contents.com/27/56/56/72/27565672_57334515_1000.jpg",
        "Other Images URL": [
            "https://cdn-images.farfetch-contents.com/27/56/56/72/27565672_57334514_1000.jpg",
            "https://cdn-images.farfetch-contents.com/27/56/56/72/27565672_57334516_1000.jpg",
            "https://cdn-images.farfetch-contents.com/27/56/56/72/27565672_57334493_1000.jpg",
            "https://cdn-images.farfetch-contents.com/27/56/56/72/27565672_57334485_1000.jpg"
        ],
        "Colors": "Black",
        "Variations": "",
        "Sizes": "",
        "Other Details": "",
        "Availability": "In Stock",
        "Number of Items in Stock": 1,
        "Last Update": "",
        "Creation Date": "2025-01-16 21:15:11"
    }
]